LICENSE
README.md
setup.cfg
setup.py
docs/About.rst
docs/Changelog.rst
src/senaite/__init__.py
src/senaite.core.spotlight.egg-info/PKG-INFO
src/senaite.core.spotlight.egg-info/SOURCES.txt
src/senaite.core.spotlight.egg-info/dependency_links.txt
src/senaite.core.spotlight.egg-info/entry_points.txt
src/senaite.core.spotlight.egg-info/namespace_packages.txt
src/senaite.core.spotlight.egg-info/not-zip-safe
src/senaite.core.spotlight.egg-info/requires.txt
src/senaite.core.spotlight.egg-info/top_level.txt
src/senaite/core/__init__.py
src/senaite/core/spotlight/__init__.py
src/senaite/core/spotlight/adapters.py
src/senaite/core/spotlight/configure.zcml
src/senaite/core/spotlight/interfaces.py
src/senaite/core/spotlight/setuphandlers.py
src/senaite/core/spotlight/viewlets.py
src/senaite/core/spotlight/views.py
src/senaite/core/spotlight/profiles/default/cssregistry.xml
src/senaite/core/spotlight/profiles/default/jsregistry.xml
src/senaite/core/spotlight/profiles/default/metadata.xml
src/senaite/core/spotlight/profiles/default/senaite.core.spotlight.txt
src/senaite/core/spotlight/profiles/uninstall/cssregistry.xml
src/senaite/core/spotlight/profiles/uninstall/jsregistry.xml
src/senaite/core/spotlight/profiles/uninstall/metadata.xml
src/senaite/core/spotlight/profiles/uninstall/senaite.core.spotlight.uninstall.txt
src/senaite/core/spotlight/static/js/senaite.core.spotlight.js
src/senaite/core/spotlight/templates/spotlight.pt
src/senaite/core/spotlight/templates/spotlight_trigger_viewlet.pt
src/senaite/core/spotlight/templates/spotlight_viewlet.pt