Metadata-Version: 2.1
Name: senaite.core.spotlight
Version: 1.0.0
Summary: MacOS like Spotlight search
Home-page: https://github.com/senaite/senaite.core.supermodel
Author: RIDING BYTES & NARALABS
Author-email: senaite@senaite.com
License: GPLv2
Platform: UNKNOWN
Classifier: Framework :: Plone
Classifier: Framework :: Zope2
Classifier: Programming Language :: Python
Classifier: Development Status :: 5 - Production/Stable
Classifier: License :: OSI Approved :: GNU General Public License v2 (GPLv2)
Provides-Extra: test
